napari_dvid/__init__.py
napari_dvid/_dock_widget.py
napari_dvid/_reader.py
napari_dvid/_version.py
napari_dvid/_tests/__init__.py
napari_dvid/_tests/test_reader.py
napari_dvid-0.2.0.dist-info/LICENSE
napari_dvid-0.2.0.dist-info/METADATA
napari_dvid-0.2.0.dist-info/WHEEL
napari_dvid-0.2.0.dist-info/entry_points.txt
napari_dvid-0.2.0.dist-info/top_level.txt
napari_dvid-0.2.0.dist-info/RECORD
