Metadata-Version: 2.1
Name: napari-dvid
Version: 0.2.0
Summary: DVID loader for napari, from a url
Home-page: https://github.com/emmazhou/napari-dvid
Author: Emma Zhou
Author-email: emma@emmazhou.com
License: MIT
Project-URL: Bug Tracker, https://github.com/emmazhou/napari-dvid/issues
Project-URL: Documentation, https://github.com/emmazhou/napari-dvid#README.md
Project-URL: Source Code, https://github.com/emmazhou/napari-dvid
Project-URL: User Support, https://github.com/emmazhou/napari-dvid/issues
Platform: UNKNOWN
Classifier: Development Status :: 2 - Pre-Alpha
Classifier: Intended Audience :: Developers
Classifier: Framework :: napari
Classifier: Topic :: Software Development :: Testing
Classifier: Programming Language :: Python
Classifier: Programming Language :: Python :: 3
Classifier: Programming Language :: Python :: 3.7
Classifier: Programming Language :: Python :: 3.8
Classifier: Programming Language :: Python :: 3.9
Classifier: Operating System :: OS Independent
Classifier: License :: OSI Approved :: MIT License
Requires-Python: >=3.7
License-File: LICENSE
Requires-Dist: napari-plugin-engine (>=0.1.4)
Requires-Dist: numpy
Requires-Dist: requests
